casepy/__init__.py
casepy/combination_generator.py
casepy/instant_method.py
casepy/permutation_generator.py
casepy/simple_methods.py
casepy/utils.py
casepy-0.2.0.dist-info/LICENSE
casepy-0.2.0.dist-info/METADATA
casepy-0.2.0.dist-info/WHEEL
casepy-0.2.0.dist-info/top_level.txt
casepy-0.2.0.dist-info/RECORD
