Metadata-Version: 2.1
Name: casepy
Version: 0.2.0
Summary: A Python package for generating cases in a list.
Home-page: https://github.com/DongHoon5793/casepy
Author: DongHoon Kim
Author-email: donghoon5793@gmail.com
License: MIT
Platform: UNKNOWN
License-File: LICENSE
